fast_alpr/__init__.py
fast_alpr/alpr.py
fast_alpr/base.py
fast_alpr/default_detector.py
fast_alpr/default_ocr.py
fast_alpr-0.3.0.dist-info/METADATA
fast_alpr-0.3.0.dist-info/WHEEL
fast_alpr-0.3.0.dist-info/licenses/LICENSE
fast_alpr-0.3.0.dist-info/RECORD
