Metadata-Version: 2.4
Name: fast-alpr
Version: 0.3.0
Summary: Fast Automatic License Plate Recognition.
Author-email: ankandrew <61120139+ankandrew@users.noreply.github.com>
License-Expression: MIT
License-File: LICENSE
Keywords: computer-vision,deep-learning,image-processing,license-plate-ocr,object-detection,onnx,plate-detection
Classifier: Intended Audience :: Developers
Classifier: Intended Audience :: Education
Classifier: Intended Audience :: Science/Research
Classifier: Operating System :: OS Independent
Classifier: Topic :: Scientific/Engineering
Classifier: Topic :: Scientific/Engineering :: Artificial Intelligence
Classifier: Topic :: Software Development
Classifier: Topic :: Software Development :: Build Tools
Classifier: Topic :: Software Development :: Libraries
Classifier: Topic :: Software Development :: Libraries :: Python Modules
Classifier: Typing :: Typed
Requires-Python: <4.0,>=3.10
Requires-Dist: fast-plate-ocr>=1.0.0
Requires-Dist: open-image-models>=0.4.0
Requires-Dist: opencv-python-headless>=4.9.0.80
Provides-Extra: onnx
Requires-Dist: onnxruntime>=1.19.2; extra == 'onnx'
Provides-Extra: onnx-directml
Requires-Dist: onnxruntime-directml>=1.19.2; extra == 'onnx-directml'
Provides-Extra: onnx-gpu
Requires-Dist: onnxruntime-gpu>=1.19.2; extra == 'onnx-gpu'
Provides-Extra: onnx-openvino
Requires-Dist: onnxruntime-openvino>=1.19.2; extra == 'onnx-openvino'
Provides-Extra: onnx-qnn
Requires-Dist: onnxruntime-qnn>=1.19.2; extra == 'onnx-qnn'
